{
	"name": "PL_SQL_MIGRATION_FAIL_CASE",
	"properties": {
		"activities": [
			{
				"name": "copy_data_sql_csv",
				"type": "Copy",
				"dependsOn": [],
				"policy": {
					"timeout": "0.12:00:00",
					"retry": 0,
					"retryIntervalInSeconds": 30,
					"secureOutput": false,
					"secureInput": false
				},
				"userProperties": [],
				"typeProperties": {
					"source": {
						"type": "SqlServerSource",
						"queryTimeout": "02:00:00",
						"partitionOption": "None"
					},
					"sink": {
						"type": "DelimitedTextSink",
						"storeSettings": {
							"type": "AzureBlobStorageWriteSettings"
						},
						"formatSettings": {
							"type": "DelimitedTextWriteSettings",
							"quoteAllText": true,
							"fileExtension": ".txt"
						}
					},
					"enableStaging": false,
					"translator": {
						"type": "TabularTranslator",
						"typeConversion": true,
						"typeConversionSettings": {
							"allowDataTruncation": true,
							"treatBooleanAsNumber": false
						}
					}
				},
				"inputs": [
					{
						"referenceName": "DS_SqlServer",
						"type": "DatasetReference"
					}
				],
				"outputs": [
					{
						"referenceName": "DelimitedTextcsv",
						"type": "DatasetReference"
					}
				]
			},
			{
				"name": "copy_success",
				"type": "SqlServerStoredProcedure",
				"dependsOn": [
					{
						"activity": "Fail1",
						"dependencyConditions": [
							"Failed"
						]
					}
				],
				"policy": {
					"timeout": "0.12:00:00",
					"retry": 0,
					"retryIntervalInSeconds": 30,
					"secureOutput": false,
					"secureInput": false
				},
				"userProperties": [],
				"typeProperties": {
					"storedProcedureName": "[audit].[loadstatus]",
					"storedProcedureParameters": {
						"dataread": {
							"value": {
								"value": "@activity('copy_data_sql_csv').output.dataRead",
								"type": "Expression"
							},
							"type": "String"
						},
						"errorid": {
							"value": {
								"value": "@activity('Fail1').output.errorCode",
								"type": "Expression"
							},
							"type": "String"
						},
						"errormessage": {
							"value": {
								"value": "@activity('Fail1').output.message",
								"type": "Expression"
							},
							"type": "String"
						},
						"loadstatus": {
							"value": {
								"value": "@activity('copy_data_sql_csv').output.executionDetails[0].status",
								"type": "Expression"
							},
							"type": "String"
						},
						"TableName": {
							"value": {
								"value": "@concat(pipeline().parameters.schemaname,'_',pipeline().parameters.tablename)\n",
								"type": "Expression"
							},
							"type": "String"
						}
					}
				},
				"linkedServiceName": {
					"referenceName": "LS_SqlServer1",
					"type": "LinkedServiceReference"
				}
			},
			{
				"name": "Fail1",
				"type": "Fail",
				"dependsOn": [
					{
						"activity": "copy_data_sql_csv",
						"dependencyConditions": [
							"Succeeded"
						]
					}
				],
				"userProperties": [],
				"typeProperties": {
					"message": "simulated_failure",
					"errorCode": "001"
				}
			}
		],
		"parameters": {
			"schemaname": {
				"type": "string",
				"defaultValue": "demo"
			},
			"tablename": {
				"type": "string",
				"defaultValue": "table_name"
			}
		},
		"annotations": [],
		"lastPublishTime": "2025-11-18T15:28:19Z"
	},
	"type": "Microsoft.DataFactory/factories/pipelines"
}